sdr_hazards_classification/__init__.py
sdr_hazards_classification/prep_utils.py
sdr_hazards_classification/sdr_api.py
sdr_hazards_classification/sdr_classifier.py
sdr_hazards_classification/sdr_data_preparer.py
sdr_hazards_classification/vectorizers.py
sdr_hazards_classification/data/Abnormal_Vibration.csv
sdr_hazards_classification/data/Corrosion_Limit.csv
sdr_hazards_classification/data/Degraded_Controllability.csv
sdr_hazards_classification/data/Depressurization.csv
sdr_hazards_classification/data/Emergency_Equipment.csv
sdr_hazards_classification/data/Engine.csv
sdr_hazards_classification/data/Fire.csv
sdr_hazards_classification/data/Flight_Crew.csv
sdr_hazards_classification/data/Fuel.csv
sdr_hazards_classification/data/General_Equipment.csv
sdr_hazards_classification/data/Non_Hazards.csv
sdr_hazards_classification/data/Parts_Departing_Aircraft.csv
sdr_hazards_classification/data/Reject_To_Takeoff.csv
sdr_hazards_classification/data/Runway_Excursion.csv
sdr_hazards_classification/data/SDR_Example.csv
sdr_hazards_classification/data/Structure.csv
sdr_hazards_classification/data/Takeoff_Landing.csv
sdr_hazards_classification/model/sdr-corrosion-limit.config
sdr_hazards_classification/model/sdr-corrosion-limit.model
sdr_hazards_classification/model/sdr-degraded-controllability.config
sdr_hazards_classification/model/sdr-degraded-controllability.model
sdr_hazards_classification/model/sdr-depressurization.config
sdr_hazards_classification/model/sdr-depressurization.model
sdr_hazards_classification/model/sdr-emergency-equipment.config
sdr_hazards_classification/model/sdr-emergency-equipment.model
sdr_hazards_classification/model/sdr-engine.config
sdr_hazards_classification/model/sdr-engine.model
sdr_hazards_classification/model/sdr-fire.config
sdr_hazards_classification/model/sdr-fire.model
sdr_hazards_classification/model/sdr-flight-crew.config
sdr_hazards_classification/model/sdr-flight-crew.model
sdr_hazards_classification/model/sdr-fuel.config
sdr_hazards_classification-1.0.0.dist-info/LICENSE
sdr_hazards_classification-1.0.0.dist-info/METADATA
sdr_hazards_classification-1.0.0.dist-info/WHEEL
sdr_hazards_classification-1.0.0.dist-info/top_level.txt
sdr_hazards_classification-1.0.0.dist-info/RECORD
