Metadata-Version: 2.1
Name: sdr-hazards-classification
Version: 1.0.0
Summary: Package to classify aviation safety hazards from FAA Service Difficulty Reports data
Home-page: 
Author: Hai Nguyen
Author-email: hai.c.nguyen@boeing.com
Classifier: Programming Language :: Python :: 3
Classifier: License :: OSI Approved :: MIT License
Classifier: Operating System :: OS Independent
Requires-Python: >=3.8
License-File: LICENSE
Requires-Dist: pandas >=1.1.5
Requires-Dist: scikit-learn >=1.3.2
Requires-Dist: xgboost
